publisher/__init__.py
publisher/admin.py
publisher/managers.py
publisher/middleware.py
publisher/models.py
publisher/signals.py
publisher/utils.py
publisher/views.py
publisher/management/__init__.py
publisher/management/commands/__init__.py
publisher/management/commands/publish_model.py
publisher/management/commands/update_permissions.py
publisher/static/publisher/publisher.css
publisher/static/publisher/publisher.js
publisher/static/publisher/images/icons.png
publisher/templates/publisher/change_form.html
publisher/templates/publisher/change_list_publish.html
publisher/templates/publisher/change_list_publish_status.html
publisher/templates/publisher/hvad/change_form.html
publisher/templates/publisher/parler/change_form.html
tests/__init__.py
tests/manage.py
tests/settings.py
tests/urls.py
tests/myapp/__init__.py
tests/myapp/admin.py
tests/myapp/models.py
tests/myapp/tests.py
django_model_publisher_mj-0.6.1.dist-info/AUTHORS.rst
django_model_publisher_mj-0.6.1.dist-info/LICENSE
django_model_publisher_mj-0.6.1.dist-info/METADATA
django_model_publisher_mj-0.6.1.dist-info/WHEEL
django_model_publisher_mj-0.6.1.dist-info/top_level.txt
django_model_publisher_mj-0.6.1.dist-info/RECORD
