Metadata-Version: 2.1
Name: django-model-publisher-mj
Version: 0.6.1
Summary: Handy mixin/abstract class for providing a "publisher workflow" to arbitrary Django models.
Home-page: https://github.com/mojob/django-model-publisher-mj
Author: Rich Temple
Author-email: rtemple@celerity.com
License: UNKNOWN
Platform: UNKNOWN
Classifier: Framework :: Django
